aiodiscover/__init__.py
aiodiscover/discovery.py
aiodiscover/network.py
aiodiscover/tests/__init__.py
aiodiscover/tests/conftest.py
aiodiscover/tests/test_discovery.py
aiodiscover/tests/test_init.py
aiodiscover/tests/test_network.py
aiodiscover/util.py
aiodiscover-2.7.0.dist-info/LICENSE
aiodiscover-2.7.0.dist-info/METADATA
aiodiscover-2.7.0.dist-info/WHEEL
aiodiscover-2.7.0.dist-info/RECORD
