Metadata-Version: 2.3
Name: aiodiscover
Version: 2.7.0
Summary: Discover hosts by arp and ptr lookup
License: Apache-2.0
Author: J. Nick Koston
Author-email: nick@koston.org
Requires-Python: >=3.9
Classifier: Development Status :: 5 - Production/Stable
Classifier: Intended Audience :: Developers
Classifier: License :: OSI Approved :: Apache Software License
Classifier: Natural Language :: English
Classifier: Operating System :: OS Independent
Classifier: Programming Language :: Python :: 3
Classifier: Programming Language :: Python :: 3.9
Classifier: Programming Language :: Python :: 3.10
Classifier: Programming Language :: Python :: 3.11
Classifier: Programming Language :: Python :: 3.12
Classifier: Programming Language :: Python :: 3.13
Classifier: Topic :: Software Development :: Libraries
Requires-Dist: aiodns (>=3.1.1)
Requires-Dist: async_timeout (>=4.0.1) ; python_version < "3.11"
Requires-Dist: cached_ipaddress (>=0.2.0)
Requires-Dist: ifaddr (>0.0.0)
Requires-Dist: netifaces (>=0.11.0)
Requires-Dist: pyroute2 (>=0.7.3)
Project-URL: Bug Tracker, https://github.com/bluetooth-devices/aiodiscover/issues
Project-URL: Changelog, https://github.com/bluetooth-devices/aiodiscover/blob/main/CHANGELOG.md
Project-URL: Documentation, https://aiodiscover.readthedocs.io
Project-URL: Repository, https://github.com/bluetooth-devices/aiodiscover
